coki/__init__.py
coki/coki-buy.bat
coki/coki-gen-credentials.bat
coki/coki-orders.bat
coki/coki-portfolio.bat
coki/coki-scr.bat
coki/coki-sell.bat
coki/coki.bat
coki/coki_buy.py
coki/coki_cancel.py
coki/coki_cli.py
coki/coki_gen_credentials.py
coki/coki_orders.py
coki/coki_portfolio.py
coki/coki_scr.py
coki/coki_sell.py
coki/funcs.py
coki/test.ipynb
coki-0.4.2.dist-info/METADATA
coki-0.4.2.dist-info/WHEEL
coki-0.4.2.dist-info/licenses/LICENSE
coki-0.4.2.dist-info/RECORD
