Metadata-Version: 2.1
Name: coki
Version: 0.4.2
Summary: Coki: un paquete para revisar los precios de Cocos
Author-email: Lucas Abbate <abbatelucas@gmail.com>, Nicolás Castro <nicolaspcastro@gmail.com>
License-File: LICENSE
Classifier: Development Status :: 2 - Pre-Alpha
Classifier: License :: OSI Approved :: MIT License
Classifier: Operating System :: Microsoft :: Windows :: Windows 10
Classifier: Programming Language :: Python :: 3
Requires-Python: >=3.8
Requires-Dist: cryptography
Requires-Dist: hatchling
Requires-Dist: numpy
Requires-Dist: pandas
Requires-Dist: requests
Requires-Dist: tabulate
